apiverve_currencysymbols/__init__.py
apiverve_currencysymbols/apiClient.py
apiverve_currencysymbols/exceptions.py
apiverve_currencysymbols/setup.py
apiverve_currencysymbols/setup_dep.py
apiverve_currencysymbols/tests/__init__.py
apiverve_currencysymbols/tests/test_api.py
apiverve_currencysymbols-1.1.7.dist-info/LICENSE
apiverve_currencysymbols-1.1.7.dist-info/METADATA
apiverve_currencysymbols-1.1.7.dist-info/WHEEL
apiverve_currencysymbols-1.1.7.dist-info/top_level.txt
apiverve_currencysymbols-1.1.7.dist-info/RECORD
